pyttyd/__init__.py
pyttyd/__main__.py
pyttyd/app.py
pyttyd/common.py
pyttyd/pty.py
pyttyd/static/css/xterm.css
pyttyd/static/img/favicon-32x32.png
pyttyd/static/img/favicon.ico
pyttyd/static/js/tty.js
pyttyd/static/js/xterm-addon-fit.js
pyttyd/static/js/xterm-addon-fit.js.map
pyttyd/static/js/xterm.js
pyttyd/static/js/xterm.js.map
pyttyd/test/__init__.py
pyttyd/test/test_rsa.py
pyttyd-1.1.1.dist-info/LICENSE
pyttyd-1.1.1.dist-info/METADATA
pyttyd-1.1.1.dist-info/WHEEL
pyttyd-1.1.1.dist-info/entry_points.txt
pyttyd-1.1.1.dist-info/top_level.txt
pyttyd-1.1.1.dist-info/RECORD
