Metadata-Version: 2.1
Name: pyttyd
Version: 1.1.1
Summary: devtool show by browser
Home-page: https://zhanglaiya.github.io/
Author: zhanglaiya
Author-email: 315396460@qq.com
Maintainer: zhanglaiya
Maintainer-email: 315396460@qq.com
License: Apache
Project-URL: Source Code, https://github.com/zhanglaiya/pyttyd/
Classifier: Development Status :: 5 - Production/Stable
Classifier: Intended Audience :: Developers
Classifier: License :: OSI Approved :: MIT License
Classifier: Operating System :: OS Independent
Classifier: Programming Language :: Python :: 3
Requires-Python: >=3.7
License-File: LICENSE
Requires-Dist: fastapi
Requires-Dist: uvicorn
Requires-Dist: websockets
